diofant/__init__.py
diofant/__main__.py
diofant/abc.py
diofant/config.py
diofant/calculus/__init__.py
diofant/calculus/gruntz.py
diofant/calculus/limits.py
diofant/calculus/optimization.py
diofant/calculus/order.py
diofant/calculus/residues.py
diofant/calculus/singularities.py
diofant/combinatorics/__init__.py
diofant/combinatorics/generators.py
diofant/combinatorics/graycode.py
diofant/combinatorics/group_constructs.py
diofant/combinatorics/named_groups.py
diofant/combinatorics/partitions.py
diofant/combinatorics/perm_groups.py
diofant/combinatorics/permutations.py
diofant/combinatorics/polyhedron.py
diofant/combinatorics/prufer.py
diofant/combinatorics/subsets.py
diofant/combinatorics/tensor_can.py
diofant/combinatorics/testutil.py
diofant/combinatorics/util.py
diofant/concrete/__init__.py
diofant/concrete/delta.py
diofant/concrete/expr_with_intlimits.py
diofant/concrete/expr_with_limits.py
diofant/concrete/gosper.py
diofant/concrete/products.py
diofant/concrete/summations.py
diofant/core/__init__.py
diofant/core/add.py
diofant/core/alphabets.py
diofant/core/assumptions.py
diofant/core/basic.py
diofant/core/cache.py
diofant/core/compatibility.py
diofant/core/containers.py
diofant/core/coreerrors.py
diofant/core/decorators.py
diofant/core/evalf.py
diofant/core/evaluate.py
diofant/core/expr.py
diofant/core/exprtools.py
diofant/core/facts.py
diofant/core/function.py
diofant/core/logic.py
diofant/core/mod.py
diofant/core/mul.py
diofant/core/multidimensional.py
diofant/core/numbers.py
diofant/core/operations.py
diofant/core/power.py
diofant/core/relational.py
diofant/core/rules.py
diofant/core/singleton.py
diofant/core/strategies.py
diofant/core/symbol.py
diofant/core/sympify.py
diofant/core/trace.py
diofant/domains/__init__.py
diofant/domains/algebraicfield.py
diofant/domains/characteristiczero.py
diofant/domains/complexfield.py
diofant/domains/compositedomain.py
diofant/domains/domain.py
diofant/domains/domainelement.py
diofant/domains/expressiondomain.py
Diofant-0.15.0.dist-info/LICENSE.rst
Diofant-0.15.0.dist-info/METADATA
Diofant-0.15.0.dist-info/WHEEL
Diofant-0.15.0.dist-info/top_level.txt
Diofant-0.15.0.dist-info/zip-safe
Diofant-0.15.0.dist-info/RECORD
